elaina_triehard-0.2.0.dist-info/METADATA
elaina_triehard-0.2.0.dist-info/RECORD
elaina_triehard-0.2.0.dist-info/WHEEL
elaina_triehard-0.2.0.dist-info/top_level.txt
tests/__init__.py
elaina_triehard/impl_c.cpython-311-x86_64-linux-musl.so
elaina_triehard/impl_py.py
elaina_triehard/impl_c.pyx
elaina_triehard/__init__.py
elaina_triehard/impl_c.pyi
