Metadata-Version: 2.1
Name: elaina-triehard
Version: 0.2.0
Summary: Default template for PDM package
Author-email: Elaina <GreyElaina@outlook.com>
License: MIT
Requires-Python: >=3.9
